livebridge_scribblelive
