Metadata-Version: 1.2
Name: livebridge-scribblelive
Version: 0.6.0
Summary: Scribblelive plugin for Livebridge.
Home-page: https://github.com/dpa-newslab/livebridge-scribblelive
Author: dpa-infocom GmbH
Maintainer: Martin Borho
Maintainer-email: martin@borho.net
License: Apache Software License (http://www.apache.org/licenses/LICENSE-2.0)
Keywords: liveticker,scribblelive,syndication
Platform: UNKNOWN
Classifier: Programming Language :: Python :: 3.5
Classifier: Topic :: Communications :: Chat
Classifier: Development Status :: 5 - Production/Stable
Classifier: License :: OSI Approved :: Apache Software License
Classifier: Intended Audience :: Other Audience
Classifier: Operating System :: POSIX :: Linux
Classifier: Environment :: Console
Classifier: Environment :: Plugins
